google/cloud/dataproc/__init__.py
google/cloud/dataproc/gapic_version.py
google/cloud/dataproc/py.typed
google/cloud/dataproc_v1/__init__.py
google/cloud/dataproc_v1/gapic_metadata.json
google/cloud/dataproc_v1/gapic_version.py
google/cloud/dataproc_v1/py.typed
google/cloud/dataproc_v1/services/__init__.py
google/cloud/dataproc_v1/services/autoscaling_policy_service/__init__.py
google/cloud/dataproc_v1/services/autoscaling_policy_service/async_client.py
google/cloud/dataproc_v1/services/autoscaling_policy_service/client.py
google/cloud/dataproc_v1/services/autoscaling_policy_service/pagers.py
google/cloud/dataproc_v1/services/autoscaling_policy_service/transports/__init__.py
google/cloud/dataproc_v1/services/autoscaling_policy_service/transports/base.py
google/cloud/dataproc_v1/services/autoscaling_policy_service/transports/grpc.py
google/cloud/dataproc_v1/services/autoscaling_policy_service/transports/grpc_asyncio.py
google/cloud/dataproc_v1/services/autoscaling_policy_service/transports/rest.py
google/cloud/dataproc_v1/services/autoscaling_policy_service/transports/rest_base.py
google/cloud/dataproc_v1/services/batch_controller/__init__.py
google/cloud/dataproc_v1/services/batch_controller/async_client.py
google/cloud/dataproc_v1/services/batch_controller/client.py
google/cloud/dataproc_v1/services/batch_controller/pagers.py
google/cloud/dataproc_v1/services/batch_controller/transports/__init__.py
google/cloud/dataproc_v1/services/batch_controller/transports/base.py
google/cloud/dataproc_v1/services/batch_controller/transports/grpc.py
google/cloud/dataproc_v1/services/batch_controller/transports/grpc_asyncio.py
google/cloud/dataproc_v1/services/batch_controller/transports/rest.py
google/cloud/dataproc_v1/services/batch_controller/transports/rest_base.py
google/cloud/dataproc_v1/services/cluster_controller/__init__.py
google/cloud/dataproc_v1/services/cluster_controller/async_client.py
google/cloud/dataproc_v1/services/cluster_controller/client.py
google_cloud_dataproc-5.19.0.dist-info/licenses/LICENSE
google_cloud_dataproc-5.19.0.dist-info/METADATA
google_cloud_dataproc-5.19.0.dist-info/WHEEL
google_cloud_dataproc-5.19.0.dist-info/top_level.txt
google_cloud_dataproc-5.19.0.dist-info/RECORD
